srai_core/__init__.py
srai_core/command_handler_base.py
srai_core/command_handler_ssh.py
srai_core/command_handler_subprocess.py
srai_core/encoder_base.py
srai_core/encoder_wrapper.py
srai_core/model/annotation.py
srai_core/model/docker_registry_base.py
srai_core/model/docker_registry_ecr.py
srai_core/model/encoder_header.py
srai_core/model/encoding.py
srai_core/model/instance_header.py
srai_core/model/source_header.py
srai_core/script/__init__.py
srai_core/script/build_docker_remote_ssh.py
srai_core/script/list_container_status_ssh.py
srai_core/script/srai_build.py
srai_core/script/srai_container_logs.py
srai_core/script/srai_containers_list.py
srai_core/script/srai_deploy.py
srai_core/script/srai_docker_stop.py
srai_core/script/srai_help.py
srai_core/script/srai_image_list.py
srai_core/script/srai_killall.py
srai_core/script/srai_release.py
srai_core/script/srai_release_code_public.py
srai_core/script/srai_release_docker_aws_ssh.py
srai_core/store/__init__.py
srai_core/store/bytes_store_base.py
srai_core/store/bytes_store_disk.py
srai_core/store/bytes_store_memory.py
srai_core/store/bytes_store_mongo.py
srai_core/store/bytes_store_s3.py
srai_core/store/database_base.py
srai_core/store/database_disk.py
srai_core/store/database_memory.py
srai_core/store/database_mongo.py
srai_core/store/database_s3.py
srai_core/store/dir_store_base.py
srai_core/store/dir_store_bytes_store.py
srai_core/store/document_store_base.py
srai_core/store/document_store_cached.py
srai_core/store/document_store_disk.py
srai_core/store/document_store_memory.py
srai_core/store/document_store_mongo.py
srai_core/store/file_store_disk.py
srai_core/store/object_store.py
srai_core/store/source_store.py
srai_core/tools_docker.py
srai_core/tools_ec2.py
srai_core/tools_env.py
srai_core/tools_s3.py
srai_core-0.15.9.dist-info/entry_points.txt
srai_core-0.15.9.dist-info/LICENSE.txt
srai_core-0.15.9.dist-info/METADATA
srai_core-0.15.9.dist-info/WHEEL
srai_core-0.15.9.dist-info/RECORD
