Metadata-Version: 2.1
Name: srai-core
Version: 0.15.9
Summary: A library core functions used in other SRAI libraries.
Home-page: https://github.com/southriverai/srai-core
License: MIT
Keywords: SRAI,TOOLS
Author: Jaap Oosterbroek
Author-email: jaap.oosterbroek@southriverai.com
Requires-Python: >=3.10,<4.0
Classifier: License :: OSI Approved :: MIT License
Classifier: Programming Language :: Python :: 3
Classifier: Programming Language :: Python :: 3.10
Classifier: Programming Language :: Python :: 3.11
Classifier: Programming Language :: Python :: 3.12
Requires-Dist: boto3 (>=1.18.61,<2.0.0)
Requires-Dist: paramiko (>=3.3.1,<4.0.0)
Requires-Dist: pydantic (>=2.8.2,<3.0.0)
Requires-Dist: pymongo (>=4.6.1,<5.0.0)
Project-URL: Repository, https://github.com/southriverai/srai-core
